[
  { "pickNumber": 1, "team": "Raiders", "playerName": "Fernando Mendoza", "position": "QB" },
  { "pickNumber": 2, "team": "Jets", "playerName": "David Bailey", "position": "EDGE" },
  { "pickNumber": 3, "team": "Cardinals", "playerName": "Francis Mauigoa", "position": "OT" },
  { "pickNumber": 4, "team": "Titans", "playerName": "Jeremiyah Love", "position": "RB" },
  { "pickNumber": 5, "team": "Giants", "playerName": "Caleb Downs", "position": "S" },
  { "pickNumber": 6, "team": "Browns", "playerName": "Carnell Tate", "position": "WR" },
  { "pickNumber": 7, "team": "Commanders", "playerName": "Sonny Styles", "position": "LB" },
  { "pickNumber": 8, "team": "Saints", "playerName": "Rueben Bain Jr.", "position": "EDGE" },
  { "pickNumber": 9, "team": "Chiefs", "playerName": "Arvell Reese", "position": "EDGE" },
  { "pickNumber": 10, "team": "Giants", "playerName": "Mansoor Delane", "position": "CB" },
  { "pickNumber": 11, "team": "Dolphins", "playerName": "Makai Lemon", "position": "WR" },
  { "pickNumber": 12, "team": "Cowboys", "playerName": "Jordyn Tyson", "position": "WR" },
  { "pickNumber": 13, "team": "Rams", "playerName": "Kenyon Sadiq", "position": "TE" },
  { "pickNumber": 14, "team": "Ravens", "playerName": "Spencer Fano", "position": "OL" },
  { "pickNumber": 15, "team": "Buccaneers", "playerName": "Jermod McCoy", "position": "CB" },
  { "pickNumber": 16, "team": "Jets", "playerName": "Omar Cooper Jr.", "position": "WR" },
  { "pickNumber": 17, "team": "Lions", "playerName": "Monroe Freeling", "position": "OT" },
  { "pickNumber": 18, "team": "Vikings", "playerName": "Dillon Thieneman", "position": "S" },
  { "pickNumber": 19, "team": "Panthers", "playerName": "Kadyn Proctor", "position": "OT" },
  { "pickNumber": 20, "team": "Cowboys", "playerName": "Keldric Faulk", "position": "EDGE" },
  { "pickNumber": 21, "team": "Steelers", "playerName": "Olaivavega Ioane", "position": "G" },
  { "pickNumber": 22, "team": "Chargers", "playerName": "Peter Woods", "position": "DT" },
  { "pickNumber": 23, "team": "Eagles", "playerName": "Blake Miller", "position": "OT" },
  { "pickNumber": 24, "team": "Browns", "playerName": "Max Iheanachor", "position": "OT" },
  { "pickNumber": 25, "team": "Bears", "playerName": "Zion Young", "position": "EDGE" },
  { "pickNumber": 26, "team": "Bills", "playerName": "Kayden McDonald", "position": "DT" },
  { "pickNumber": 27, "team": "49ers", "playerName": "Caleb Lomu", "position": "OT" },
  { "pickNumber": 28, "team": "Texans", "playerName": "Christen Miller", "position": "DT" },
  { "pickNumber": 29, "team": "Chiefs", "playerName": "Malachi Lawrence", "position": "EDGE" },
  { "pickNumber": 30, "team": "Dolphins", "playerName": "Akheem Mesidor", "position": "EDGE" },
  { "pickNumber": 31, "team": "Patriots", "playerName": "R Mason Thomas", "position": "EDGE" },
  { "pickNumber": 32, "team": "Seahawks", "playerName": "Jadarian Price", "position": "RB" }
]
